setup.cfg
setup.py
src/epitropos/__init__.py
src/epitropos.egg-info/PKG-INFO
src/epitropos.egg-info/SOURCES.txt
src/epitropos.egg-info/dependency_links.txt
src/epitropos.egg-info/entry_points.txt
src/epitropos.egg-info/requires.txt
src/epitropos.egg-info/top_level.txt
src/epitropos.egg-info/zip-safe
src/epitropos/cmd/__init__.py
src/epitropos/cmd/config.py
src/epitropos/cmd/console.py
src/epitropos/cmd/debug.py
src/epitropos/cmd/help.py
src/epitropos/cmd/plugin.py
src/epitropos/cmd/server.py
src/epitropos/oauth2/__init__.py
src/epitropos/oauth2/errors.py
src/epitropos/oauth2/responses.py
src/epitropos/plugin/__init__.py
src/epitropos/plugin/ldap_auth.py
src/epitropos/plugin/redis_store.py
src/epitropos/routes/__init__.py
src/epitropos/routes/health.py
src/epitropos/routes/token.py
src/epitropos/util/__init__.py
src/epitropos/util/identity.py